mahoraga/__init__.py
mahoraga/__main__.py
mahoraga/_asgi/__init__.py
mahoraga/_asgi/_app.py
mahoraga/_asgi/_server.py
mahoraga/_cli/__init__.py
mahoraga/_cli/mahoraga.conf.jinja
mahoraga/_cli/mahoraga.toml.jinja
mahoraga/_cli/nginx.conf.jinja
mahoraga/_conda/__init__.py
mahoraga/_conda/_models.py
mahoraga/_conda/_packages.py
mahoraga/_conda/_parselmouth.py
mahoraga/_conda/_repodata.py
mahoraga/_conda/_sharded_repodata.py
mahoraga/_conda/_utils.py
mahoraga/_core/__init__.py
mahoraga/_core/_config.py
mahoraga/_core/_context.py
mahoraga/_core/_metadata.py
mahoraga/_core/_stream.py
mahoraga/_jsdelivr/__init__.py
mahoraga/_jsdelivr/_gh.py
mahoraga/_jsdelivr/_npm.py
mahoraga/_jsdelivr/_pyodide.py
mahoraga/_jsdelivr/_utils.py
mahoraga/_preload.py
mahoraga/_pypi/__init__.py
mahoraga/_pypi/_models.py
mahoraga/_pypi/_packages.py
mahoraga/_pypi/_simple.py
mahoraga/_python.py
mahoraga/_static/get_pixi.py
mahoraga/_static/panel_support.py
mahoraga/_uv.py
mahoraga/py.typed
mahoraga-0.5.0.dist-info/WHEEL
mahoraga-0.5.0.dist-info/entry_points.txt
mahoraga-0.5.0.dist-info/METADATA
mahoraga-0.5.0.dist-info/RECORD
